<feature>
    <area>
        <point x="-687.719970703125" y="2960.0478515625"/>
        <point x="2430.788818359375" y="1787.437866210938"/>
        <point x="719.412109375" y="-741.5968017578125"/>
        <point x="408.8289184570313" y="-1616.300415039063"/>
        <point x="-484.8900756835938" y="-2960.0478515625"/>
        <point x="-2430.788818359375" y="-2047.313842773438"/>
        <point x="-2227.958984375" y="-411.9981689453125"/>
        <point x="-2240.635986328125" y="-44.369140625"/>
        <point x="-1828.6376953125" y="817.65771484375"/>
        <point x="-1429.316528320313" y="1502.20849609375"/>
        <point x="-1099.718017578125" y="2002.944580078125"/>
        <point x="-941.2572021484375" y="2491.00390625"/>
        <point x="-687.719970703125" y="2960.0478515625"/>
    </area>
    <hintLine>
        <point x="-491.228515625" y="69.72265625"/>
        <point x="60.21511840820313" y="545.1051025390625"/>
        <point x="282.0602416992188" y="1318.393920898438"/>
    </hintLine>
    <avenues filename="new-york.xml.avenues.gsm"/>
    <streets filename="new-york.xml.streets.gsm"/>
</feature>
