<feature>
    <area>
        <point x="-3719.17724609375" y="1803.950927734375"/>
        <point x="-3174.20458984375" y="1782.662963867188"/>
        <point x="-2756.9599609375" y="1825.239013671875"/>
        <point x="-2663.292724609375" y="1182.341430664063"/>
        <point x="-2714.3837890625" y="714.0054931640625"/>
        <point x="-2761.217529296875" y="547.9591064453125"/>
        <point x="-2859.142333984375" y="220.1239776611328"/>
        <point x="-3067.7646484375" y="88.13839721679688"/>
        <point x="-3459.463623046875" y="-1.271190881729126"/>
        <point x="-3876.70849609375" y="79.62319946289063"/>
        <point x="-3897.996337890625" y="667.1719360351563"/>
        <point x="-3795.81396484375" y="1310.069458007813"/>
        <point x="-3761.753173828125" y="1612.359008789063"/>
        <point x="-3719.17724609375" y="1803.950927734375"/>
    </area>
    <hintLine>
        <point x="-3186.977294921875" y="931.14306640625"/>
    </hintLine>
    <avenues filename="plaza.xml.avenues.gsm"/>
    <streets filename="plaza.xml.streets.gsm"/>
</feature>
